{
	"configurations" : 
	[
		{
			"directories" : 
			[
				{
					"build" : ".",
					"jsonFile" : "directory-.-Debug-f5ebdc15457944623624.json",
					"minimumCMakeVersion" : 
					{
						"string" : "3.29"
					},
					"projectIndex" : 0,
					"source" : ".",
					"targetIndexes" : 
					[
						0,
						1,
						2,
						3,
						4,
						5,
						6,
						7,
						8,
						9,
						10,
						11,
						12,
						13,
						14,
						15,
						16,
						17
					]
				}
			],
			"name" : "Debug",
			"projects" : 
			[
				{
					"directoryIndexes" : 
					[
						0
					],
					"name" : "HH",
					"targetIndexes" : 
					[
						0,
						1,
						2,
						3,
						4,
						5,
						6,
						7,
						8,
						9,
						10,
						11,
						12,
						13,
						14,
						15,
						16,
						17
					]
				}
			],
			"targets" : 
			[
				{
					"directoryIndex" : 0,
					"id" : "HttpParser_test::@6890427a1f51a3e7e1df",
					"jsonFile" : "target-HttpParser_test-Debug-e704a886aff7c904b19d.json",
					"name" : "HttpParser_test",
					"projectIndex" : 0
				},
				{
					"directoryIndex" : 0,
					"id" : "Tcp_server_test::@6890427a1f51a3e7e1df",
					"jsonFile" : "target-Tcp_server_test-Debug-60aa46837627e8102c9b.json",
					"name" : "Tcp_server_test",
					"projectIndex" : 0
				},
				{
					"directoryIndex" : 0,
					"id" : "address_test::@6890427a1f51a3e7e1df",
					"jsonFile" : "target-address_test-Debug-00d2ac178441d73fd7db.json",
					"name" : "address_test",
					"projectIndex" : 0
				},
				{
					"directoryIndex" : 0,
					"id" : "bytearray_test::@6890427a1f51a3e7e1df",
					"jsonFile" : "target-bytearray_test-Debug-e659369fa72a8015e072.json",
					"name" : "bytearray_test",
					"projectIndex" : 0
				},
				{
					"directoryIndex" : 0,
					"id" : "common_objs::@6890427a1f51a3e7e1df",
					"jsonFile" : "target-common_objs-Debug-e742026d070244c5957b.json",
					"name" : "common_objs",
					"projectIndex" : 0
				},
				{
					"directoryIndex" : 0,
					"id" : "config_test::@6890427a1f51a3e7e1df",
					"jsonFile" : "target-config_test-Debug-367ce1618af32bf20953.json",
					"name" : "config_test",
					"projectIndex" : 0
				},
				{
					"directoryIndex" : 0,
					"id" : "echo_server::@6890427a1f51a3e7e1df",
					"jsonFile" : "target-echo_server-Debug-2665a3ae0ff58c20b5dd.json",
					"name" : "echo_server",
					"projectIndex" : 0
				},
				{
					"directoryIndex" : 0,
					"id" : "hook_test::@6890427a1f51a3e7e1df",
					"jsonFile" : "target-hook_test-Debug-eedfa3bf3e3feaef5126.json",
					"name" : "hook_test",
					"projectIndex" : 0
				},
				{
					"directoryIndex" : 0,
					"id" : "httpConnection_test::@6890427a1f51a3e7e1df",
					"jsonFile" : "target-httpConnection_test-Debug-d4cc70ce2581485bf693.json",
					"name" : "httpConnection_test",
					"projectIndex" : 0
				},
				{
					"directoryIndex" : 0,
					"id" : "httpUrl_test::@6890427a1f51a3e7e1df",
					"jsonFile" : "target-httpUrl_test-Debug-ceaf48487116ce3975d4.json",
					"name" : "httpUrl_test",
					"projectIndex" : 0
				},
				{
					"directoryIndex" : 0,
					"id" : "http_test::@6890427a1f51a3e7e1df",
					"jsonFile" : "target-http_test-Debug-e018e7108826adc3dc87.json",
					"name" : "http_test",
					"projectIndex" : 0
				},
				{
					"directoryIndex" : 0,
					"id" : "httpserver_test::@6890427a1f51a3e7e1df",
					"jsonFile" : "target-httpserver_test-Debug-ca9bc04a6b54e44393ec.json",
					"name" : "httpserver_test",
					"projectIndex" : 0
				},
				{
					"directoryIndex" : 0,
					"id" : "iomanager_test::@6890427a1f51a3e7e1df",
					"jsonFile" : "target-iomanager_test-Debug-18b09c0a87e039d2e342.json",
					"name" : "iomanager_test",
					"projectIndex" : 0
				},
				{
					"directoryIndex" : 0,
					"id" : "log_test::@6890427a1f51a3e7e1df",
					"jsonFile" : "target-log_test-Debug-1c8e8141d475d79f31dc.json",
					"name" : "log_test",
					"projectIndex" : 0
				},
				{
					"directoryIndex" : 0,
					"id" : "pthread_test::@6890427a1f51a3e7e1df",
					"jsonFile" : "target-pthread_test-Debug-db67ee751ca3b4b9bb56.json",
					"name" : "pthread_test",
					"projectIndex" : 0
				},
				{
					"directoryIndex" : 0,
					"id" : "scheduler_test::@6890427a1f51a3e7e1df",
					"jsonFile" : "target-scheduler_test-Debug-ba639010ab31ff3bef98.json",
					"name" : "scheduler_test",
					"projectIndex" : 0
				},
				{
					"directoryIndex" : 0,
					"id" : "socket_test::@6890427a1f51a3e7e1df",
					"jsonFile" : "target-socket_test-Debug-5d4d8f6dc87d3e778173.json",
					"name" : "socket_test",
					"projectIndex" : 0
				},
				{
					"directoryIndex" : 0,
					"id" : "utils_test::@6890427a1f51a3e7e1df",
					"jsonFile" : "target-utils_test-Debug-cd25ade3e5a21e703f87.json",
					"name" : "utils_test",
					"projectIndex" : 0
				}
			]
		}
	],
	"kind" : "codemodel",
	"paths" : 
	{
		"build" : "/home/hh/HH/cmake-build-debug",
		"source" : "/home/hh/HH"
	},
	"version" : 
	{
		"major" : 2,
		"minor" : 7
	}
}
